livelossplot/__init__.py
livelossplot/main_logger.py
livelossplot/plot_losses.py
livelossplot/version.py
livelossplot/inputs/__init__.py
livelossplot/inputs/generic_keras.py
livelossplot/inputs/keras.py
livelossplot/inputs/poutyne.py
livelossplot/inputs/pytorch_ignite.py
livelossplot/inputs/tf_keras.py
livelossplot/outputs/__init__.py
livelossplot/outputs/base_output.py
livelossplot/outputs/bokeh_plot.py
livelossplot/outputs/extrema_printer.py
livelossplot/outputs/matplotlib_plot.py
livelossplot/outputs/matplotlib_subplots.py
livelossplot/outputs/neptune_logger.py
livelossplot/outputs/tensorboard_logger.py
livelossplot/outputs/tensorboard_tf_logger.py
livelossplot-0.5.6.dist-info/LICENSE.txt
livelossplot-0.5.6.dist-info/METADATA
livelossplot-0.5.6.dist-info/WHEEL
livelossplot-0.5.6.dist-info/top_level.txt
livelossplot-0.5.6.dist-info/RECORD
