Metadata-Version: 2.1
Name: livelossplot
Version: 0.5.6
Summary: Live training loss plot in Jupyter Notebook for Keras, PyTorch and others.
Home-page: https://github.com/stared/livelossplot
Author: Piotr Migdał
Author-email: pmigdal@gmail.com
License: MIT
Keywords: keras,pytorch,plot,chart,deep-learning
Classifier: Development Status :: 4 - Beta
Classifier: Framework :: Jupyter
Classifier: Intended Audience :: Developers
Classifier: Intended Audience :: Education
Classifier: Intended Audience :: Science/Research
Classifier: Topic :: Scientific/Engineering
Classifier: Topic :: Scientific/Engineering :: Artificial Intelligence
Classifier: Topic :: Scientific/Engineering :: Visualization
Classifier: License :: OSI Approved :: MIT License
Classifier: Programming Language :: Python :: 3
Classifier: Programming Language :: Python :: 3.7
Classifier: Programming Language :: Python :: 3.8
Classifier: Programming Language :: Python :: 3.9
Classifier: Programming Language :: Python :: 3.10
Classifier: Programming Language :: Python :: 3.11
Classifier: Programming Language :: Python :: 3.12
Requires-Python: >=3.7
License-File: LICENSE.txt
Requires-Dist: matplotlib
Requires-Dist: bokeh
Requires-Dist: ipython ==7.* ; python_version < "3.8"
Requires-Dist: numpy <1.22 ; python_version < "3.8"
